ks3/__init__.py
ks3/acl.py
ks3/auth.py
ks3/authV4.py
ks3/billing.py
ks3/bucket.py
ks3/bucketDecompressPolicy.py
ks3/bucketlistresultset.py
ks3/compat.py
ks3/connection.py
ks3/copy.py
ks3/crc64_combine.py
ks3/deletemarker.py
ks3/download.py
ks3/encryptFp.py
ks3/encryption.py
ks3/exception.py
ks3/handler.py
ks3/http.py
ks3/key.py
ks3/keyfile.py
ks3/multipart.py
ks3/prefix.py
ks3/provider.py
ks3/responseResult.py
ks3/resultset.py
ks3/share_encryption.py
ks3/sts.py
ks3/tagging.py
ks3/upload.py
ks3/user.py
ks3/utils.py
ks3/xmlParsers/VpcAccessBlock.py
ks3/xmlParsers/__init__.py
ks3/xmlParsers/bucketAccessMonitor.py
ks3/xmlParsers/bucketCors.py
ks3/xmlParsers/bucketCrossReplicate.py
ks3/xmlParsers/bucketDataRedundancySwitch.py
ks3/xmlParsers/bucketEncryption.py
ks3/xmlParsers/bucketInventory.py
ks3/xmlParsers/bucketLifecycle.py
ks3/xmlParsers/bucketLogging.py
ks3/xmlParsers/bucketMirror.py
ks3/xmlParsers/bucketQos.py
ks3/xmlParsers/bucketQuota.py
ks3/xmlParsers/bucketRetention.py
ks3/xmlParsers/bucketTransferAcceleration.py
ks3/xmlParsers/bucketVersioning.py
ks3/xmlParsers/objectMigration.py
ks3/xmlParsers/requesterQos.py
ks3sdk-1.15.0.dist-info/LICENSE
ks3sdk-1.15.0.dist-info/METADATA
ks3sdk-1.15.0.dist-info/WHEEL
ks3sdk-1.15.0.dist-info/top_level.txt
ks3sdk-1.15.0.dist-info/RECORD
