Metadata-Version: 2.1
Name: ks3sdk
Version: 1.15.0
Summary: Ksyun KS3 SDK
Home-page: https://gitee.com/ks3sdk/ks3-python-sdk
Author: ksc_ks3
Author-email: ksc_ks3@kingsoft.com
License: MIT
Platform: UNKNOWN
Classifier: Development Status :: 5 - Production/Stable
Classifier: Intended Audience :: Developers
Classifier: License :: OSI Approved :: MIT License
Classifier: Operating System :: OS Independent
Classifier: Programming Language :: Python
Classifier: Programming Language :: Python :: 3
Classifier: Programming Language :: Python :: 3.7
Classifier: Programming Language :: Python :: 3.8
Requires-Python: >=3.6
License-File: LICENSE
Requires-Dist: six
Requires-Dist: python-dateutil
Requires-Dist: aiofiles (~=23.2.1)
Requires-Dist: crcmod (~=1.7)
Requires-Dist: pycryptodome (~=3.20.0)
Requires-Dist: requests
